<annotation>
	<folder>sow</folder>
	<filename>d9ca5899fb6482a538a71cf8f0ac5f05.jpg</filename>
	<path>D:\sow\d9ca5899fb6482a538a71cf8f0ac5f05.jpg</path>
	<source>
		<database>Unknown</database>
	</source>
	<size>
		<width>590</width>
		<height>714</height>
		<depth>3</depth>
	</size>
	<segmented>0</segmented>
	<object>
		<name>window</name>
		<pose>Unspecified</pose>
		<truncated>0</truncated>
		<difficult>0</difficult>
		<bndbox>
			<xmin>68</xmin>
			<ymin>119</ymin>
			<xmax>87</xmax>
			<ymax>224</ymax>
		</bndbox>
	</object>
	<object>
		<name>window</name>
		<pose>Unspecified</pose>
		<truncated>0</truncated>
		<difficult>0</difficult>
		<bndbox>
			<xmin>64</xmin>
			<ymin>306</ymin>
			<xmax>98</xmax>
			<ymax>378</ymax>
		</bndbox>
	</object>
	<object>
		<name>wall</name>
		<pose>Unspecified</pose>
		<truncated>0</truncated>
		<difficult>0</difficult>
		<bndbox>
			<xmin>64</xmin>
			<ymin>371</ymin>
			<xmax>88</xmax>
			<ymax>593</ymax>
		</bndbox>
	</object>
	<object>
		<name>wall</name>
		<pose>Unspecified</pose>
		<truncated>0</truncated>
		<difficult>0</difficult>
		<bndbox>
			<xmin>69</xmin>
			<ymin>568</ymin>
			<xmax>164</xmax>
			<ymax>598</ymax>
		</bndbox>
	</object>
	<object>
		<name>wall</name>
		<pose>Unspecified</pose>
		<truncated>0</truncated>
		<difficult>0</difficult>
		<bndbox>
			<xmin>256</xmin>
			<ymin>565</ymin>
			<xmax>371</xmax>
			<ymax>600</ymax>
		</bndbox>
	</object>
	<object>
		<name>wall</name>
		<pose>Unspecified</pose>
		<truncated>0</truncated>
		<difficult>0</difficult>
		<bndbox>
			<xmin>416</xmin>
			<ymin>569</ymin>
			<xmax>518</xmax>
			<ymax>593</ymax>
		</bndbox>
	</object>
	<object>
		<name>wall</name>
		<pose>Unspecified</pose>
		<truncated>0</truncated>
		<difficult>0</difficult>
		<bndbox>
			<xmin>490</xmin>
			<ymin>534</ymin>
			<xmax>524</xmax>
			<ymax>591</ymax>
		</bndbox>
	</object>
	<object>
		<name>wall</name>
		<pose>Unspecified</pose>
		<truncated>0</truncated>
		<difficult>0</difficult>
		<bndbox>
			<xmin>493</xmin>
			<ymin>337</ymin>
			<xmax>526</xmax>
			<ymax>444</ymax>
		</bndbox>
	</object>
	<object>
		<name>wall</name>
		<pose>Unspecified</pose>
		<truncated>0</truncated>
		<difficult>0</difficult>
		<bndbox>
			<xmin>307</xmin>
			<ymin>376</ymin>
			<xmax>519</xmax>
			<ymax>404</ymax>
		</bndbox>
	</object>
	<object>
		<name>wall</name>
		<pose>Unspecified</pose>
		<truncated>0</truncated>
		<difficult>0</difficult>
		<bndbox>
			<xmin>69</xmin>
			<ymin>217</ymin>
			<xmax>88</xmax>
			<ymax>311</ymax>
		</bndbox>
	</object>
	<object>
		<name>wall</name>
		<pose>Unspecified</pose>
		<truncated>0</truncated>
		<difficult>0</difficult>
		<bndbox>
			<xmin>72</xmin>
			<ymin>272</ymin>
			<xmax>242</xmax>
			<ymax>295</ymax>
		</bndbox>
	</object>
	<object>
		<name>wall</name>
		<pose>Unspecified</pose>
		<truncated>0</truncated>
		<difficult>0</difficult>
		<bndbox>
			<xmin>232</xmin>
			<ymin>273</ymin>
			<xmax>257</xmax>
			<ymax>336</ymax>
		</bndbox>
	</object>
	<object>
		<name>wall</name>
		<pose>Unspecified</pose>
		<truncated>0</truncated>
		<difficult>0</difficult>
		<bndbox>
			<xmin>69</xmin>
			<ymin>50</ymin>
			<xmax>91</xmax>
			<ymax>128</ymax>
		</bndbox>
	</object>
	<object>
		<name>wall</name>
		<pose>Unspecified</pose>
		<truncated>0</truncated>
		<difficult>0</difficult>
		<bndbox>
			<xmin>69</xmin>
			<ymin>46</ymin>
			<xmax>517</xmax>
			<ymax>73</ymax>
		</bndbox>
	</object>
	<object>
		<name>wall</name>
		<pose>Unspecified</pose>
		<truncated>0</truncated>
		<difficult>0</difficult>
		<bndbox>
			<xmin>229</xmin>
			<ymin>53</ymin>
			<xmax>250</xmax>
			<ymax>238</ymax>
		</bndbox>
	</object>
	<object>
		<name>wall</name>
		<pose>Unspecified</pose>
		<truncated>0</truncated>
		<difficult>0</difficult>
		<bndbox>
			<xmin>297</xmin>
			<ymin>218</ymin>
			<xmax>517</xmax>
			<ymax>234</ymax>
		</bndbox>
	</object>
	<object>
		<name>wall</name>
		<pose>Unspecified</pose>
		<truncated>0</truncated>
		<difficult>0</difficult>
		<bndbox>
			<xmin>492</xmin>
			<ymin>173</ymin>
			<xmax>519</xmax>
			<ymax>281</ymax>
		</bndbox>
	</object>
	<object>
		<name>wall</name>
		<pose>Unspecified</pose>
		<truncated>0</truncated>
		<difficult>0</difficult>
		<bndbox>
			<xmin>498</xmin>
			<ymin>54</ymin>
			<xmax>519</xmax>
			<ymax>113</ymax>
		</bndbox>
	</object>
	<object>
		<name>door</name>
		<pose>Unspecified</pose>
		<truncated>0</truncated>
		<difficult>0</difficult>
		<bndbox>
			<xmin>188</xmin>
			<ymin>212</ymin>
			<xmax>248</xmax>
			<ymax>284</ymax>
		</bndbox>
	</object>
	<object>
		<name>door</name>
		<pose>Unspecified</pose>
		<truncated>0</truncated>
		<difficult>0</difficult>
		<bndbox>
			<xmin>182</xmin>
			<ymin>327</ymin>
			<xmax>249</xmax>
			<ymax>387</ymax>
		</bndbox>
	</object>
	<object>
		<name>door</name>
		<pose>Unspecified</pose>
		<truncated>0</truncated>
		<difficult>0</difficult>
		<bndbox>
			<xmin>302</xmin>
			<ymin>328</ymin>
			<xmax>372</xmax>
			<ymax>386</ymax>
		</bndbox>
	</object>
	<object>
		<name>door</name>
		<pose>Unspecified</pose>
		<truncated>0</truncated>
		<difficult>0</difficult>
		<bndbox>
			<xmin>345</xmin>
			<ymin>515</ymin>
			<xmax>429</xmax>
			<ymax>585</ymax>
		</bndbox>
	</object>
	<object>
		<name>door</name>
		<pose>Unspecified</pose>
		<truncated>0</truncated>
		<difficult>0</difficult>
		<bndbox>
			<xmin>245</xmin>
			<ymin>145</ymin>
			<xmax>306</xmax>
			<ymax>234</ymax>
		</bndbox>
	</object>
	<object>
		<name>wall</name>
		<pose>Unspecified</pose>
		<truncated>0</truncated>
		<difficult>0</difficult>
		<bndbox>
			<xmin>293</xmin>
			<ymin>216</ymin>
			<xmax>332</xmax>
			<ymax>331</ymax>
		</bndbox>
	</object>
	<object>
		<name>window</name>
		<pose>Unspecified</pose>
		<truncated>0</truncated>
		<difficult>0</difficult>
		<bndbox>
			<xmin>491</xmin>
			<ymin>109</ymin>
			<xmax>525</xmax>
			<ymax>178</ymax>
		</bndbox>
	</object>
	<object>
		<name>window</name>
		<pose>Unspecified</pose>
		<truncated>0</truncated>
		<difficult>0</difficult>
		<bndbox>
			<xmin>492</xmin>
			<ymin>275</ymin>
			<xmax>526</xmax>
			<ymax>340</ymax>
		</bndbox>
	</object>
	<object>
		<name>window</name>
		<pose>Unspecified</pose>
		<truncated>0</truncated>
		<difficult>0</difficult>
		<bndbox>
			<xmin>488</xmin>
			<ymin>435</ymin>
			<xmax>529</xmax>
			<ymax>538</ymax>
		</bndbox>
	</object>
	<object>
		<name>wall</name>
		<pose>Unspecified</pose>
		<truncated>0</truncated>
		<difficult>0</difficult>
		<bndbox>
			<xmin>78</xmin>
			<ymin>372</ymin>
			<xmax>249</xmax>
			<ymax>402</ymax>
		</bndbox>
	</object>
	<object>
		<name>room</name>
		<pose>Unspecified</pose>
		<truncated>0</truncated>
		<difficult>0</difficult>
		<bndbox>
			<xmin>76</xmin>
			<ymin>58</ymin>
			<xmax>247</xmax>
			<ymax>285</ymax>
		</bndbox>
	</object>
	<object>
		<name>room</name>
		<pose>Unspecified</pose>
		<truncated>0</truncated>
		<difficult>0</difficult>
		<bndbox>
			<xmin>72</xmin>
			<ymin>282</ymin>
			<xmax>251</xmax>
			<ymax>394</ymax>
		</bndbox>
	</object>
	<object>
		<name>room</name>
		<pose>Unspecified</pose>
		<truncated>0</truncated>
		<difficult>0</difficult>
		<bndbox>
			<xmin>244</xmin>
			<ymin>59</ymin>
			<xmax>514</xmax>
			<ymax>225</ymax>
		</bndbox>
	</object>
	<object>
		<name>room</name>
		<pose>Unspecified</pose>
		<truncated>0</truncated>
		<difficult>0</difficult>
		<bndbox>
			<xmin>309</xmin>
			<ymin>225</ymin>
			<xmax>516</xmax>
			<ymax>393</ymax>
		</bndbox>
	</object>
	<object>
		<name>room</name>
		<pose>Unspecified</pose>
		<truncated>0</truncated>
		<difficult>0</difficult>
		<bndbox>
			<xmin>243</xmin>
			<ymin>222</ymin>
			<xmax>312</xmax>
			<ymax>395</ymax>
		</bndbox>
	</object>
	<object>
		<name>room</name>
		<pose>Unspecified</pose>
		<truncated>0</truncated>
		<difficult>0</difficult>
		<bndbox>
			<xmin>74</xmin>
			<ymin>386</ymin>
			<xmax>516</xmax>
			<ymax>595</ymax>
		</bndbox>
	</object>
</annotation>
